<?xml version="1.0" encoding="UTF-8"?><record_update table="atf_output_variable">
    <atf_output_variable action="INSERT_OR_UPDATE">
        <active>true</active>
        <array>false</array>
        <attributes>element_mapping_provider=com.glide.automated_testing_framework.ATFVariableElementMapper</attributes>
        <audit>false</audit>
        <calculation><![CDATA[(function calculatedFieldValue(current) {

	// Add your code here
	return '';  // return the calculated value

})(current);]]></calculation>
        <choice/>
        <choice_field/>
        <choice_table/>
        <column_label>Record</column_label>
        <comments/>
        <create_roles/>
        <default_value/>
        <defaultsort/>
        <delete_roles/>
        <dependent>table</dependent>
        <dependent_on_field>table</dependent_on_field>
        <display>false</display>
        <dynamic_creation>false</dynamic_creation>
        <dynamic_creation_script/>
        <dynamic_default_value/>
        <dynamic_ref_qual/>
        <element>record_id</element>
        <element_reference>false</element_reference>
        <foreign_database/>
        <formula/>
        <function_definition/>
        <function_field>false</function_field>
        <help/>
        <hint/>
        <internal_type display_value="">document_id</internal_type>
        <label>Record</label>
        <mandatory>false</mandatory>
        <max_length>32</max_length>
        <model display_value="Click a UI Action (SP PXP)">32444d34971b5110d545b18e6253af91</model>
        <model_id>32444d34971b5110d545b18e6253af91</model_id>
        <model_table/>
        <name>var__m_atf_output_variable_32444d34971b5110d545b18e6253af91</name>
        <next_element/>
        <order>100</order>
        <primary>false</primary>
        <read_only>false</read_only>
        <read_roles/>
        <reference/>
        <reference_cascade_rule/>
        <reference_floats>false</reference_floats>
        <reference_key/>
        <reference_qual/>
        <reference_qual_condition/>
        <reference_type/>
        <spell_check>false</spell_check>
        <staged>false</staged>
        <sys_class_name>atf_output_variable</sys_class_name>
        <sys_created_by>admin</sys_created_by>
        <sys_created_on>2022-11-18 22:13:52</sys_created_on>
        <sys_name>Record</sys_name>
        <sys_package display_value="Portal Experience" source="x_376096_pxp">b7a339a3971011102f77b4b3f153afd7</sys_package>
        <sys_policy/>
        <sys_scope display_value="Portal Experience">b7a339a3971011102f77b4b3f153afd7</sys_scope>
        <sys_update_name>atf_output_variable_7c9b757c97db5110d545b18e6253af6f</sys_update_name>
        <table_reference>false</table_reference>
        <text_index>false</text_index>
        <unique>false</unique>
        <use_dependent_field>true</use_dependent_field>
        <use_dynamic_default>false</use_dynamic_default>
        <use_reference_qualifier>simple</use_reference_qualifier>
        <virtual>false</virtual>
        <virtual_type>script</virtual_type>
        <widget/>
        <write_roles/>
        <xml_view>false</xml_view>
    </atf_output_variable>
</record_update>
